autoproperty/__init__.py
autoproperty/autoproperty.py
autoproperty/autoproperty.pyi
autoproperty/fieldvalidator.py
autoproperty/light_autoproperty.cpp
autoproperty/light_autoproperty.cpython-312-x86_64-linux-gnu.so
autoproperty/light_autoproperty.pxd
autoproperty/light_autoproperty.pyi
autoproperty/light_autoproperty.pyx
autoproperty/prop_settings.py
autoproperty/setup.py
autoproperty/autoproperty_methods/__init__.py
autoproperty/autoproperty_methods/autoproperty_base.py
autoproperty/autoproperty_methods/autoproperty_getter.py
autoproperty/autoproperty_methods/autoproperty_setter.py
autoproperty/docs/light_property_manual.md
autoproperty/docs/manual.md
autoproperty/events/context.py
autoproperty/events/data.py
autoproperty/events/event.py
autoproperty/events/filters.py
autoproperty/events/listener.py
autoproperty/exceptions/Exceptions.py
autoproperty/interfaces/autoproperty_methods/__init__.py
autoproperty/interfaces/events/__init__.py
autoproperty-0.0.60.dist-info/METADATA
autoproperty-0.0.60.dist-info/WHEEL
autoproperty-0.0.60.dist-info/licenses/LICENSE
autoproperty-0.0.60.dist-info/RECORD
