Metadata-Version: 2.4
Name: autoproperty
Version: 0.0.60
Summary: Library for creating autogenerated property with type validation.
Project-URL: Homepage, https://github.com/Provonsal/autoproperty
Project-URL: Issues, https://github.com/Provonsal/autoproperty/issues
Project-URL: Latest, https://github.com/Provonsal/autoproperty/releases/latest
Project-URL: Discord, https://discord.gg/B9UpRRUxQS
Author-email: Provonsal <alecsw86@gmail.com>
License-File: LICENSE
Classifier: License :: OSI Approved :: MIT License
Classifier: Operating System :: OS Independent
Classifier: Programming Language :: Python :: 3
Requires-Python: >=3.10.0
Requires-Dist: pydantic
